sripprocess/__init__.py
sripprocess/pprocess.py
sripprocess-1.0.dist-info/LICENSE.txt
sripprocess-1.0.dist-info/METADATA
sripprocess-1.0.dist-info/WHEEL
sripprocess-1.0.dist-info/top_level.txt
sripprocess-1.0.dist-info/RECORD
