Metadata-Version: 2.1
Name: sripprocess
Version: 1.0
Summary: text preprocessing package
Home-page: https://github.com/sriram7797/preprocess
Author: sriram
Author-email: shreeram7797@gmail.com
License: UNKNOWN
Platform: UNKNOWN
Classifier: Programming Language :: Python :: 3
Classifier: License :: OSI Approved :: MIT License
Classifier: Operating System :: OS Independent
Requires-Python: >=3.0
